magicway_payment_gateway/__init__.py
magicway_payment_gateway/momagic_connector.py
magicway_payment_gateway/status_code.py
magicway_payment_gateway-1.0.0.dist-info/LICENSE
magicway_payment_gateway-1.0.0.dist-info/METADATA
magicway_payment_gateway-1.0.0.dist-info/WHEEL
magicway_payment_gateway-1.0.0.dist-info/top_level.txt
magicway_payment_gateway-1.0.0.dist-info/RECORD
