Metadata-Version: 2.1
Name: magicway-payment-gateway
Version: 1.0.0
Summary: MagicWay Payment Gateway
Home-page: https://github.com/momagicbd/MoMagic-Python
Author: Arifur Rahman
Author-email: info@momagicbd.com
License: UNKNOWN
Keywords: magicway,payment-gateway,e-commerce,shop,local-payment-gateway,international-payment-gateway
Platform: UNKNOWN
Classifier: Development Status :: 5 - Production/Stable
Classifier: Intended Audience :: Developers
Classifier: Topic :: Software Development :: Libraries :: Python Modules
Classifier: Operating System :: OS Independent
Classifier: Programming Language :: Python :: 3
Classifier: Programming Language :: Python :: 3.1
Classifier: Programming Language :: Python :: 3.2
Classifier: Programming Language :: Python :: 3.3
Classifier: Programming Language :: Python :: 3.4
Classifier: Programming Language :: Python :: 3.5
Classifier: Programming Language :: Python :: 3.6
Classifier: Programming Language :: Python :: 3.7
Classifier: Programming Language :: Python :: 3.8
Classifier: Programming Language :: Python :: 3.9
Classifier: Programming Language :: Python :: 3 :: Only
License-File: LICENSE
Requires-Dist: requests
